<?xml version="1.0" encoding="utf-8" ?>
<schema name="stackoverflow-questions" version="1.4">
    <uniqueKey>question_id</uniqueKey>
    <defaultSearchField>title</defaultSearchField>
    <types>
        <fieldType name="string" class="solr.StrField"/>

        <!-- From the standard solr example: -->
        <!-- A text field with defaults appropriate for English, plus
        aggressive word-splitting and autophrase features enabled.
        This field is just like text_en, except it adds
        WordDelimiterFilter to enable splitting and matching of
        words on case-change, alpha numeric boundaries, and
        non-alphanumeric chars.  This means certain compound word
        cases will work, for example query "wi fi" will match
        document "WiFi" or "wi-fi".
        -->
        <fieldType name="text_en_splitting" class="solr.TextField" positionIncrementGap="100"
                   autoGeneratePhraseQueries="true">
            <analyzer type="index">
                <tokenizer class="solr.WhitespaceTokenizerFactory"/>
                <!-- in this example, we will only use synonyms at query time
                <filter class="solr.SynonymFilterFactory" synonyms="index_synonyms.txt" ignoreCase="true" expand="false"/>
                -->
                <!-- Case insensitive stop word removal.
                -->
                <filter class="solr.StopFilterFactory"
                        ignoreCase="true"
                        words="lang/stopwords_en.txt"
                        />
                <filter class="solr.WordDelimiterFilterFactory" generateWordParts="1" generateNumberParts="1"
                        catenateWords="1" catenateNumbers="1" catenateAll="0" splitOnCaseChange="1"/>
                <filter class="solr.LowerCaseFilterFactory"/>
                <filter class="solr.KeywordMarkerFilterFactory" protected="protwords.txt"/>
                <filter class="solr.PorterStemFilterFactory"/>
            </analyzer>
            <analyzer type="query">
                <tokenizer class="solr.WhitespaceTokenizerFactory"/>
                <filter class="solr.SynonymFilterFactory" synonyms="synonyms.txt" ignoreCase="true" expand="true"/>
                <filter class="solr.StopFilterFactory"
                        ignoreCase="true"
                        words="lang/stopwords_en.txt"
                        />
                <filter class="solr.WordDelimiterFilterFactory" generateWordParts="1" generateNumberParts="1"
                        catenateWords="0" catenateNumbers="0" catenateAll="0" splitOnCaseChange="1"/>
                <filter class="solr.LowerCaseFilterFactory"/>
                <filter class="solr.KeywordMarkerFilterFactory" protected="protwords.txt"/>
                <filter class="solr.PorterStemFilterFactory"/>
            </analyzer>
        </fieldType>

        <fieldType name="boolean" class="solr.BoolField" sortMissingLast="true"/>
        <fieldType name="long" class="solr.TrieLongField" precisionStep="0" positionIncrementGap="0"/>
        <fieldType name="int" class="solr.TrieIntField" precisionStep="0" positionIncrementGap="0"/>

    </types>
    <fields>
        <field name="question_id" type="long" indexed="true" stored="true" required="true"/>
        <field name="body" type="text_en_splitting" indexed="true" stored="true"/>
        <field name="is_answered" type="boolean" indexed="true" stored="true"/>
        <field name="link" type="string" indexed="true" stored="true"/>
        <field name="score" type="int" indexed="true" stored="true"/>
        <field name="tags" type="string" indexed="true" stored="true" multiValued="true"/>
        <field name="title" type="text_en_splitting" indexed="true" stored="true"/>
        <field name="creation_date" type="string" indexed="false" stored="false"/>
    </fields>
</schema>
